jetpytools/__init__.py
jetpytools/_version.py
jetpytools/py.typed
jetpytools/enums/__init__.py
jetpytools/enums/base.py
jetpytools/enums/other.py
jetpytools/exceptions/__init__.py
jetpytools/exceptions/base.py
jetpytools/exceptions/enum.py
jetpytools/exceptions/file.py
jetpytools/exceptions/generic.py
jetpytools/exceptions/module.py
jetpytools/functions/__init__.py
jetpytools/functions/funcs.py
jetpytools/functions/normalize.py
jetpytools/functions/other.py
jetpytools/types/__init__.py
jetpytools/types/builtins.py
jetpytools/types/check.py
jetpytools/types/file.py
jetpytools/types/funcs.py
jetpytools/types/generic.py
jetpytools/types/supports.py
jetpytools/types/utils.py
jetpytools/utils/__init__.py
jetpytools/utils/file.py
jetpytools/utils/funcs.py
jetpytools/utils/math.py
jetpytools/utils/ranges.py
jetpytools-2.2.5.dist-info/METADATA
jetpytools-2.2.5.dist-info/WHEEL
jetpytools-2.2.5.dist-info/licenses/LICENSE
jetpytools-2.2.5.dist-info/RECORD
